langprompt/__init__.py
langprompt/py.typed
langprompt/base/__init__.py
langprompt/base/content.py
langprompt/base/embedding.py
langprompt/base/message.py
langprompt/base/ratelimiter.py
langprompt/base/response.py
langprompt/cache/__init__.py
langprompt/embeddings/__init__.py
langprompt/embeddings/base.py
langprompt/embeddings/openai.py
langprompt/llms/__init__.py
langprompt/llms/base.py
langprompt/llms/openai.py
langprompt/llms/qianfan.py
langprompt/output_parser/__init__.py
langprompt/output_parser/base.py
langprompt/output_parser/json.py
langprompt/prompt/__init__.py
langprompt/store/__init__.py
langprompt/store/duckdb.py
langprompt/store/model.py
langprompt/store/store.py
langprompt-0.1.1.dist-info/METADATA
langprompt-0.1.1.dist-info/WHEEL
langprompt-0.1.1.dist-info/entry_points.txt
langprompt-0.1.1.dist-info/licenses/LICENSE
langprompt-0.1.1.dist-info/RECORD
