Metadata-Version: 2.4
Name: langprompt
Version: 0.1.1
Summary: Add your description here
Author-email: Tao Yang <swulling@gmail.com>
License-File: LICENSE
Requires-Python: >=3.10
Requires-Dist: duckdb>=1.1.3
Requires-Dist: jinja2>=3.1.5
Requires-Dist: json-repair>=0.35.0
Requires-Dist: openai>=1.59.5
Requires-Dist: pydantic>=2.10.4
Requires-Dist: tenacity>=8.5.0
Requires-Dist: tqdm>=4.67.1
Provides-Extra: qianfan
Requires-Dist: qianfan>=0.4.12.2; extra == 'qianfan'
Provides-Extra: test
Requires-Dist: pytest-cov>=4.1.0; extra == 'test'
Requires-Dist: pytest>=7.4.0; extra == 'test'
